[
  {
    "id": 37633,
    "name": "BENU",
    "zip_code": "85369"
  },
  {
    "id": 37634,
    "name": "FATUKONA",
    "zip_code": "85369"
  },
  {
    "id": 37635,
    "name": "HUEKNUTU",
    "zip_code": "85369"
  },
  {
    "id": 37636,
    "name": "KAUNIKI",
    "zip_code": "85369"
  },
  {
    "id": 37637,
    "name": "NOELMINA",
    "zip_code": "85369"
  },
  {
    "id": 37638,
    "name": "OELNAINENO",
    "zip_code": "85369"
  },
  {
    "id": 37639,
    "name": "OESUSU",
    "zip_code": "85369"
  },
  {
    "id": 37640,
    "name": "TAKARI",
    "zip_code": "85369"
  },
  {
    "id": 37641,
    "name": "TANINI",
    "zip_code": "85369"
  },
  {
    "id": 37642,
    "name": "TUAPANAF",
    "zip_code": "85369"
  }
]