[
  {
    "id": 57439,
    "name": "BAJO",
    "zip_code": "94479"
  },
  {
    "id": 57440,
    "name": "BERINGIN JAYA",
    "zip_code": "94479"
  },
  {
    "id": 57441,
    "name": "BOLANO",
    "zip_code": "94479"
  },
  {
    "id": 57442,
    "name": "BOLANO BARAT",
    "zip_code": "94479"
  },
  {
    "id": 57443,
    "name": "BOLANO TENGAH",
    "zip_code": "94479"
  },
  {
    "id": 57444,
    "name": "BOLANO UTARA",
    "zip_code": "94479"
  },
  {
    "id": 57445,
    "name": "LEMBAH BOMBAN",
    "zip_code": "94479"
  },
  {
    "id": 57446,
    "name": "SAMA BAHARI",
    "zip_code": "94479"
  },
  {
    "id": 57447,
    "name": "SIDOMUKTI",
    "zip_code": "94479"
  },
  {
    "id": 57448,
    "name": "SRITABAANG",
    "zip_code": "94479"
  },
  {
    "id": 57449,
    "name": "WANAMUKTI",
    "zip_code": "94479"
  },
  {
    "id": 57450,
    "name": "WANAMUKTI BARAT",
    "zip_code": "94479"
  },
  {
    "id": 57451,
    "name": "WANAMUKTI UTARA",
    "zip_code": "94479"
  }
]