[
  {
    "id": 46424,
    "name": "ASEM GEDE",
    "zip_code": "61454"
  },
  {
    "id": 46425,
    "name": "CUPAK",
    "zip_code": "61454"
  },
  {
    "id": 46426,
    "name": "KEBOAN",
    "zip_code": "61454"
  },
  {
    "id": 46427,
    "name": "KEDUNG BOGO",
    "zip_code": "61454"
  },
  {
    "id": 46428,
    "name": "KETAPANG KUNING",
    "zip_code": "61454"
  },
  {
    "id": 46429,
    "name": "KROMONG",
    "zip_code": "61454"
  },
  {
    "id": 46430,
    "name": "MANUNGGAL",
    "zip_code": "61454"
  },
  {
    "id": 46431,
    "name": "MOJODANU",
    "zip_code": "61454"
  },
  {
    "id": 46432,
    "name": "NGAMPEL",
    "zip_code": "61454"
  },
  {
    "id": 46433,
    "name": "NGUSIKAN",
    "zip_code": "61454"
  },
  {
    "id": 46434,
    "name": "SUMBER NONGKO",
    "zip_code": "61454"
  }
]