[
  {
    "id": 20302,
    "name": "BATU HAMPAR",
    "zip_code": "37163"
  },
  {
    "id": 20303,
    "name": "BEDENG DELAPAN",
    "zip_code": "37163"
  },
  {
    "id": 20304,
    "name": "BEDENG DUA",
    "zip_code": "37163"
  },
  {
    "id": 20305,
    "name": "BENTO",
    "zip_code": "37163"
  },
  {
    "id": 20306,
    "name": "ENSATU",
    "zip_code": "37163"
  },
  {
    "id": 20307,
    "name": "GIRI MULYO",
    "zip_code": "37163"
  },
  {
    "id": 20308,
    "name": "GUNUNG LABU",
    "zip_code": "37163"
  },
  {
    "id": 20309,
    "name": "KAMPUNG BARU",
    "zip_code": "37163"
  },
  {
    "id": 20310,
    "name": "KEBUN BARU",
    "zip_code": "37163"
  },
  {
    "id": 20311,
    "name": "PASAR MINGGU",
    "zip_code": "37163"
  },
  {
    "id": 20312,
    "name": "PATOK EMPAT",
    "zip_code": "37163"
  },
  {
    "id": 20313,
    "name": "SAKO DUO/DUA",
    "zip_code": "37163"
  },
  {
    "id": 20314,
    "name": "SUNGAI ASAM",
    "zip_code": "37163"
  },
  {
    "id": 20315,
    "name": "SUNGAI JAMBU",
    "zip_code": "37163"
  },
  {
    "id": 20316,
    "name": "SUNGAI KERING",
    "zip_code": "37163"
  },
  {
    "id": 20317,
    "name": "SUNGAI LINTANG",
    "zip_code": "37163"
  },
  {
    "id": 20318,
    "name": "SUNGAI RENAH",
    "zip_code": "37163"
  }
]