[
  {
    "id": 61310,
    "name": "BOJONG",
    "zip_code": "43157"
  },
  {
    "id": 61311,
    "name": "BOJONGKEMBAR",
    "zip_code": "43157"
  },
  {
    "id": 61312,
    "name": "BOJONGRAHARJA",
    "zip_code": "43157"
  },
  {
    "id": 61313,
    "name": "CIBATU",
    "zip_code": "43157"
  },
  {
    "id": 61314,
    "name": "CIKEMBAR",
    "zip_code": "43157"
  },
  {
    "id": 61315,
    "name": "CIMANGGU",
    "zip_code": "43157"
  },
  {
    "id": 61316,
    "name": "KERTARAHARJA",
    "zip_code": "43157"
  },
  {
    "id": 61317,
    "name": "PARAKANLIMA",
    "zip_code": "43157"
  },
  {
    "id": 61318,
    "name": "SUKAMAJU",
    "zip_code": "43157"
  },
  {
    "id": 61319,
    "name": "SUKAMULYA",
    "zip_code": "43157"
  }
]