[
  {
    "id": 13314,
    "name": "CIBUBUKAN",
    "zip_code": "24783"
  },
  {
    "id": 13315,
    "name": "GUHA",
    "zip_code": "24783"
  },
  {
    "id": 13316,
    "name": "KAIN GOLONG",
    "zip_code": "24783"
  },
  {
    "id": 13317,
    "name": "KUTA BATU",
    "zip_code": "24783"
  },
  {
    "id": 13318,
    "name": "KUTA KARANGAN",
    "zip_code": "24783"
  },
  {
    "id": 13319,
    "name": "KUTA TINGGI",
    "zip_code": "24783"
  },
  {
    "id": 13320,
    "name": "LAE GAMBIR",
    "zip_code": "24783"
  },
  {
    "id": 13321,
    "name": "LAE GECIH",
    "zip_code": "24783"
  },
  {
    "id": 13322,
    "name": "LAE NIPE",
    "zip_code": "24783"
  },
  {
    "id": 13323,
    "name": "LAE RIMAN",
    "zip_code": "24783"
  },
  {
    "id": 13324,
    "name": "LIPAT KAJANG",
    "zip_code": "24783"
  },
  {
    "id": 13325,
    "name": "LIPAT KAJANG ATAS",
    "zip_code": "24783"
  },
  {
    "id": 13326,
    "name": "PAKIRAMAN",
    "zip_code": "24783"
  },
  {
    "id": 13327,
    "name": "PANDAN SARI",
    "zip_code": "24783"
  },
  {
    "id": 13328,
    "name": "PANGI",
    "zip_code": "24783"
  },
  {
    "id": 13329,
    "name": "PERTABAS",
    "zip_code": "24783"
  },
  {
    "id": 13330,
    "name": "SERASAH",
    "zip_code": "24783"
  },
  {
    "id": 13331,
    "name": "SIATAS",
    "zip_code": "24783"
  },
  {
    "id": 13332,
    "name": "SILATONG",
    "zip_code": "24783"
  },
  {
    "id": 13333,
    "name": "SODODADI",
    "zip_code": "24783"
  },
  {
    "id": 13334,
    "name": "SUKAREJO",
    "zip_code": "24783"
  },
  {
    "id": 13335,
    "name": "TANJUNG MAS",
    "zip_code": "24783"
  },
  {
    "id": 13336,
    "name": "TUGAN",
    "zip_code": "24783"
  },
  {
    "id": 13337,
    "name": "TUH TUHAN",
    "zip_code": "24783"
  },
  {
    "id": 13338,
    "name": "UJUNG LIMUS",
    "zip_code": "24783"
  }
]