[
  {
    "id": 79163,
    "name": "BONTORANNU",
    "zip_code": "90126"
  },
  {
    "id": 79164,
    "name": "KAMPUNG BUYANG",
    "zip_code": "90121"
  },
  {
    "id": 79165,
    "name": "KUNJUNG MAE",
    "zip_code": "90125"
  },
  {
    "id": 79166,
    "name": "LETTE",
    "zip_code": "90123"
  },
  {
    "id": 79167,
    "name": "MARIO",
    "zip_code": "90125"
  },
  {
    "id": 79168,
    "name": "MARISO",
    "zip_code": "90122"
  },
  {
    "id": 79169,
    "name": "MATTOANGIN",
    "zip_code": "90121"
  },
  {
    "id": 79170,
    "name": "PANAMBUNGAN",
    "zip_code": "90121"
  },
  {
    "id": 79171,
    "name": "TAMARUNANG",
    "zip_code": "90126"
  }
]