[
  {
    "id": 20856,
    "name": "AUR CINO",
    "zip_code": "37259"
  },
  {
    "id": 20857,
    "name": "DUSUN BARU",
    "zip_code": "37259"
  },
  {
    "id": 20858,
    "name": "KUAMANG",
    "zip_code": "37259"
  },
  {
    "id": 20859,
    "name": "MUARA NIRO",
    "zip_code": "37259"
  },
  {
    "id": 20860,
    "name": "MUARA TABUN",
    "zip_code": "37259"
  },
  {
    "id": 20861,
    "name": "PUCUK JAMBI",
    "zip_code": "37259"
  },
  {
    "id": 20862,
    "name": "SUNGAI ABANG",
    "zip_code": "37259"
  },
  {
    "id": 20863,
    "name": "TABUN",
    "zip_code": "37259"
  },
  {
    "id": 20864,
    "name": "TELUK KAYU PUTIH",
    "zip_code": "37259"
  },
  {
    "id": 20865,
    "name": "TELUK LANCANG",
    "zip_code": "37259"
  }
]