[
  {
    "id": 18703,
    "name": "BAROS",
    "zip_code": "42173"
  },
  {
    "id": 18704,
    "name": "CISALAM",
    "zip_code": "42173"
  },
  {
    "id": 18705,
    "name": "CURUG AGUNG",
    "zip_code": "42173"
  },
  {
    "id": 18706,
    "name": "PADASUKA",
    "zip_code": "42173"
  },
  {
    "id": 18707,
    "name": "PANYIRAPAN",
    "zip_code": "42173"
  },
  {
    "id": 18708,
    "name": "SIDAMUKTI",
    "zip_code": "42173"
  },
  {
    "id": 18709,
    "name": "SINARMUKTI",
    "zip_code": "42173"
  },
  {
    "id": 18710,
    "name": "SINDANGMANDI",
    "zip_code": "42173"
  },
  {
    "id": 18711,
    "name": "SUKA INDAH",
    "zip_code": "42173"
  },
  {
    "id": 18712,
    "name": "SUKACAI",
    "zip_code": "42173"
  },
  {
    "id": 18713,
    "name": "SUKAMANAH",
    "zip_code": "42173"
  },
  {
    "id": 18714,
    "name": "SUKAMENAK",
    "zip_code": "42173"
  },
  {
    "id": 18715,
    "name": "TAMANSARI",
    "zip_code": "42173"
  },
  {
    "id": 18716,
    "name": "TEJAMARI",
    "zip_code": "42173"
  }
]