[
  {
    "id": 4590,
    "name": "BATA",
    "zip_code": "71665"
  },
  {
    "id": 4591,
    "name": "BUNTU KARAU",
    "zip_code": "71665"
  },
  {
    "id": 4592,
    "name": "GALUMBANG",
    "zip_code": "71665"
  },
  {
    "id": 4593,
    "name": "GULINGGANG",
    "zip_code": "71665"
  },
  {
    "id": 4594,
    "name": "HAMARUNG",
    "zip_code": "71665"
  },
  {
    "id": 4595,
    "name": "HUKAI",
    "zip_code": "71665"
  },
  {
    "id": 4596,
    "name": "JUAI",
    "zip_code": "71665"
  },
  {
    "id": 4597,
    "name": "LALAYAU",
    "zip_code": "71665"
  },
  {
    "id": 4598,
    "name": "MARIAS",
    "zip_code": "71665"
  },
  {
    "id": 4599,
    "name": "MIHU",
    "zip_code": "71665"
  },
  {
    "id": 4600,
    "name": "MUARA NINIAN",
    "zip_code": "71665"
  },
  {
    "id": 4601,
    "name": "MUNGKUR UYAM",
    "zip_code": "71665"
  },
  {
    "id": 4602,
    "name": "PAMURUS",
    "zip_code": "71665"
  },
  {
    "id": 4603,
    "name": "PANIMBAAN",
    "zip_code": "71665"
  },
  {
    "id": 4604,
    "name": "SEI/SUNGAI BATUNG",
    "zip_code": "71665"
  },
  {
    "id": 4605,
    "name": "SIRAP",
    "zip_code": "71665"
  },
  {
    "id": 4606,
    "name": "SUMBER REJEKI",
    "zip_code": "71665"
  },
  {
    "id": 4607,
    "name": "TAWAHAN",
    "zip_code": "71665"
  },
  {
    "id": 4608,
    "name": "TELUK BAYUR",
    "zip_code": "71665"
  },
  {
    "id": 4609,
    "name": "TIGARUN",
    "zip_code": "71665"
  },
  {
    "id": 4610,
    "name": "WONOREJO",
    "zip_code": "71665"
  }
]