[
  {
    "id": 73818,
    "name": "INAUGA",
    "zip_code": "99963"
  },
  {
    "id": 73819,
    "name": "KADUN JAYA",
    "zip_code": "99963"
  },
  {
    "id": 73820,
    "name": "KAMORO JAYA",
    "zip_code": "99963"
  },
  {
    "id": 73821,
    "name": "MANDIRI JAYA",
    "zip_code": "99963"
  },
  {
    "id": 73822,
    "name": "MAWOKAU JAYA",
    "zip_code": "99963"
  },
  {
    "id": 73823,
    "name": "NAWARIPI",
    "zip_code": "99963"
  },
  {
    "id": 73824,
    "name": "WONOSARI JAYA",
    "zip_code": "99963"
  }
]