[
  {
    "id": 10941,
    "name": "BADAR INDAH",
    "zip_code": "24652"
  },
  {
    "id": 10942,
    "name": "BATU MBERONG",
    "zip_code": "24652"
  },
  {
    "id": 10943,
    "name": "DELENG MEGAKHE",
    "zip_code": "24652"
  },
  {
    "id": 10944,
    "name": "KAMPUNG BARU",
    "zip_code": "24652"
  },
  {
    "id": 10945,
    "name": "KUMBANG INDAH",
    "zip_code": "24652"
  },
  {
    "id": 10946,
    "name": "KUMBANG JAYA",
    "zip_code": "24652"
  },
  {
    "id": 10947,
    "name": "KUTA/KUTE PASIR",
    "zip_code": "24652"
  },
  {
    "id": 10948,
    "name": "KUTA/KUTE TINGGI",
    "zip_code": "24652"
  },
  {
    "id": 10949,
    "name": "LAWE BEKUNG",
    "zip_code": "24652"
  },
  {
    "id": 10950,
    "name": "LAWE BEKUNG TAMPAHAN",
    "zip_code": "24652"
  },
  {
    "id": 10951,
    "name": "LAWE SEKEKHAH",
    "zip_code": "24652"
  },
  {
    "id": 10952,
    "name": "NATAM",
    "zip_code": "24652"
  },
  {
    "id": 10953,
    "name": "NATAM BARU",
    "zip_code": "24652"
  },
  {
    "id": 10954,
    "name": "PERANGINAN",
    "zip_code": "24652"
  },
  {
    "id": 10955,
    "name": "PURWODADI",
    "zip_code": "24652"
  },
  {
    "id": 10956,
    "name": "SALANG ALAS",
    "zip_code": "24652"
  },
  {
    "id": 10957,
    "name": "TANAH MERAH",
    "zip_code": "24652"
  },
  {
    "id": 10958,
    "name": "TANOH MEGAKHE",
    "zip_code": "24652"
  }
]