[
  {
    "id": 4837,
    "name": "BURANGRANG",
    "zip_code": "40262"
  },
  {
    "id": 4838,
    "name": "CIJAGRA",
    "zip_code": "40265"
  },
  {
    "id": 4839,
    "name": "CIKAWAO",
    "zip_code": "40261"
  },
  {
    "id": 4840,
    "name": "LINGKAR SELATAN",
    "zip_code": "40263"
  },
  {
    "id": 4841,
    "name": "MALABAR",
    "zip_code": "40262"
  },
  {
    "id": 4842,
    "name": "PALEDANG",
    "zip_code": "40261"
  },
  {
    "id": 4843,
    "name": "TURANGGA",
    "zip_code": "40264"
  }
]