[
  {
    "id": 2947,
    "name": "AGUNG",
    "zip_code": "71514"
  },
  {
    "id": 2948,
    "name": "BANYU TAJUN",
    "zip_code": "71515"
  },
  {
    "id": 2949,
    "name": "GARUNGGUNG",
    "zip_code": "71515"
  },
  {
    "id": 2950,
    "name": "HIKUN",
    "zip_code": "71515"
  },
  {
    "id": 2951,
    "name": "JANGKUNG",
    "zip_code": "71512"
  },
  {
    "id": 2952,
    "name": "JUAI",
    "zip_code": "71515"
  },
  {
    "id": 2953,
    "name": "KAMBITIN",
    "zip_code": "71515"
  },
  {
    "id": 2954,
    "name": "KAMBITIN RAYA",
    "zip_code": "71515"
  },
  {
    "id": 2955,
    "name": "KITANG",
    "zip_code": "71515"
  },
  {
    "id": 2956,
    "name": "MAHE SEBERANG",
    "zip_code": "71515"
  },
  {
    "id": 2957,
    "name": "PAMARANGAN KIWA",
    "zip_code": "71515"
  },
  {
    "id": 2958,
    "name": "PUAIN KIWA",
    "zip_code": "71515"
  },
  {
    "id": 2959,
    "name": "SEI/SUNGAI PIMPING",
    "zip_code": "71515"
  },
  {
    "id": 2960,
    "name": "TANJUNG",
    "zip_code": "71513"
  },
  {
    "id": 2961,
    "name": "WAYAU",
    "zip_code": "71515"
  }
]