[
  {
    "id": 12270,
    "name": "BALEE GANTUNG",
    "zip_code": "24183"
  },
  {
    "id": 12271,
    "name": "BLANG BAROH",
    "zip_code": "24183"
  },
  {
    "id": 12272,
    "name": "BUNGONG",
    "zip_code": "24183"
  },
  {
    "id": 12273,
    "name": "DABOIH",
    "zip_code": "24183"
  },
  {
    "id": 12274,
    "name": "GEUNTENG",
    "zip_code": "24183"
  },
  {
    "id": 12275,
    "name": "GLUMPANG BUNGKOK",
    "zip_code": "24183"
  },
  {
    "id": 12276,
    "name": "JURONG BARO",
    "zip_code": "24183"
  },
  {
    "id": 12277,
    "name": "KUMBANG TRUEUNG CAMPLI",
    "zip_code": "24183"
  },
  {
    "id": 12278,
    "name": "KUMBANG UNOE",
    "zip_code": "24183"
  },
  {
    "id": 12279,
    "name": "MANYANG",
    "zip_code": "24183"
  },
  {
    "id": 12280,
    "name": "MEE TEUMPEN (MEU TEUMPEUN)",
    "zip_code": "24183"
  },
  {
    "id": 12281,
    "name": "PALONG",
    "zip_code": "24183"
  },
  {
    "id": 12282,
    "name": "PULO IBOIH",
    "zip_code": "24183"
  },
  {
    "id": 12283,
    "name": "PULO PANJOE",
    "zip_code": "24183"
  },
  {
    "id": 12284,
    "name": "SAGOE",
    "zip_code": "24183"
  },
  {
    "id": 12285,
    "name": "SANGGET (SANGET)",
    "zip_code": "24183"
  },
  {
    "id": 12286,
    "name": "SEUKEE",
    "zip_code": "24183"
  },
  {
    "id": 12287,
    "name": "SEUREUKUI CEBREK",
    "zip_code": "24183"
  },
  {
    "id": 12288,
    "name": "SUKON PAKU",
    "zip_code": "24183"
  },
  {
    "id": 12289,
    "name": "U BUNGKOK (U BANGKOK)",
    "zip_code": "24183"
  },
  {
    "id": 12290,
    "name": "UKEE",
    "zip_code": "24183"
  }
]