[
  {
    "id": 49391,
    "name": "BAKAM",
    "zip_code": "33252"
  },
  {
    "id": 49392,
    "name": "BUKIT LAYANG",
    "zip_code": "33252"
  },
  {
    "id": 49393,
    "name": "DALIL",
    "zip_code": "33252"
  },
  {
    "id": 49394,
    "name": "KAPUK",
    "zip_code": "33252"
  },
  {
    "id": 49395,
    "name": "MABAT",
    "zip_code": "33252"
  },
  {
    "id": 49396,
    "name": "MANGKA",
    "zip_code": "33252"
  },
  {
    "id": 49397,
    "name": "MARAS SENANG",
    "zip_code": "33252"
  },
  {
    "id": 49398,
    "name": "NEKNANG",
    "zip_code": "33252"
  },
  {
    "id": 49399,
    "name": "TIANG TARA",
    "zip_code": "33252"
  }
]