[
  {
    "id": 2641,
    "name": "WONOSARI"
  },
  {
    "id": 2642,
    "name": "KARANGMOJO"
  },
  {
    "id": 2643,
    "name": "NGAWEN"
  },
  {
    "id": 2644,
    "name": "NGLIPAR"
  },
  {
    "id": 2645,
    "name": "PALIYAN"
  },
  {
    "id": 2646,
    "name": "PANGGANG"
  },
  {
    "id": 2647,
    "name": "PATUK"
  },
  {
    "id": 2648,
    "name": "PLAYEN"
  },
  {
    "id": 2649,
    "name": "PONJONG"
  },
  {
    "id": 2650,
    "name": "RONGKOP"
  },
  {
    "id": 2651,
    "name": "SEMIN"
  },
  {
    "id": 2652,
    "name": "SEMANU"
  },
  {
    "id": 2653,
    "name": "TEPUS"
  },
  {
    "id": 2654,
    "name": "GEDANG SARI"
  },
  {
    "id": 2655,
    "name": "GIRISUBO"
  },
  {
    "id": 2656,
    "name": "PURWOSARI"
  },
  {
    "id": 2657,
    "name": "SAPTO SARI"
  },
  {
    "id": 2658,
    "name": "TANJUNGSARI"
  }
]