[
  {
    "id": 15892,
    "name": "ABAIL",
    "zip_code": "23891"
  },
  {
    "id": 15893,
    "name": "BATU-BATU",
    "zip_code": "23891"
  },
  {
    "id": 15894,
    "name": "BUSUNG INDAH",
    "zip_code": "23891"
  },
  {
    "id": 15895,
    "name": "KAHAT",
    "zip_code": "23891"
  },
  {
    "id": 15896,
    "name": "LABUAH",
    "zip_code": "23891"
  },
  {
    "id": 15897,
    "name": "LANTING",
    "zip_code": "23891"
  },
  {
    "id": 15898,
    "name": "LASIKIN",
    "zip_code": "23891"
  },
  {
    "id": 15899,
    "name": "MATAN URUNG",
    "zip_code": "23891"
  },
  {
    "id": 15900,
    "name": "NANCAWA",
    "zip_code": "23891"
  },
  {
    "id": 15901,
    "name": "SIMPANG ABAIL",
    "zip_code": "23891"
  },
  {
    "id": 15902,
    "name": "SITUBUK",
    "zip_code": "23891"
  },
  {
    "id": 15903,
    "name": "SUA-SUA",
    "zip_code": "23891"
  }
]