[
  {
    "id": 34281,
    "name": "DUWET",
    "zip_code": "64174"
  },
  {
    "id": 34282,
    "name": "GADUNGAN",
    "zip_code": "64174"
  },
  {
    "id": 34283,
    "name": "JAJAR",
    "zip_code": "64174"
  },
  {
    "id": 34284,
    "name": "JANTI",
    "zip_code": "64174"
  },
  {
    "id": 34285,
    "name": "JOHO",
    "zip_code": "64174"
  },
  {
    "id": 34286,
    "name": "KARANGANYAR",
    "zip_code": "64174"
  },
  {
    "id": 34287,
    "name": "PAGU",
    "zip_code": "64174"
  },
  {
    "id": 34288,
    "name": "PLAOSAN",
    "zip_code": "64174"
  },
  {
    "id": 34289,
    "name": "POJOK",
    "zip_code": "64174"
  },
  {
    "id": 34290,
    "name": "SEGARAN",
    "zip_code": "64174"
  },
  {
    "id": 34291,
    "name": "SIDOMULYO",
    "zip_code": "64174"
  },
  {
    "id": 34292,
    "name": "SILIR",
    "zip_code": "64174"
  },
  {
    "id": 34293,
    "name": "SUMBERAGUNG",
    "zip_code": "64174"
  },
  {
    "id": 34294,
    "name": "TAWANG",
    "zip_code": "64174"
  },
  {
    "id": 34295,
    "name": "TEMPUREJO",
    "zip_code": "64174"
  },
  {
    "id": 34296,
    "name": "TUNGE",
    "zip_code": "64174"
  },
  {
    "id": 34297,
    "name": "WATES",
    "zip_code": "64174"
  },
  {
    "id": 34298,
    "name": "WONOREJO",
    "zip_code": "64174"
  }
]