[
  {
    "id": 2000,
    "name": "MASIREI"
  },
  {
    "id": 2001,
    "name": "WAROPEN BAWAH"
  },
  {
    "id": 2002,
    "name": "INGGERUS"
  },
  {
    "id": 2003,
    "name": "KIRIHI"
  },
  {
    "id": 2004,
    "name": "RISEI SAYATI"
  },
  {
    "id": 2005,
    "name": "UREI FAISEI"
  },
  {
    "id": 2006,
    "name": "DEMBA"
  },
  {
    "id": 2007,
    "name": "OUDATE"
  },
  {
    "id": 2008,
    "name": "SOYOI MAMBAI"
  },
  {
    "id": 2009,
    "name": "WAPOGA"
  },
  {
    "id": 2010,
    "name": "WONTI"
  }
]