[
  {
    "id": 6002,
    "name": "CIBODAS",
    "zip_code": "40391"
  },
  {
    "id": 6003,
    "name": "CIBOGO",
    "zip_code": "40391"
  },
  {
    "id": 6004,
    "name": "CIKAHURIPAN",
    "zip_code": "40391"
  },
  {
    "id": 6005,
    "name": "CIKIDANG",
    "zip_code": "40391"
  },
  {
    "id": 6006,
    "name": "CIKOLE",
    "zip_code": "40391"
  },
  {
    "id": 6007,
    "name": "GUDANGKAHURIPAN",
    "zip_code": "40391"
  },
  {
    "id": 6008,
    "name": "JAYAGIRI",
    "zip_code": "40391"
  },
  {
    "id": 6009,
    "name": "KAYUAMBON",
    "zip_code": "40391"
  },
  {
    "id": 6010,
    "name": "LANGENSARI",
    "zip_code": "40391"
  },
  {
    "id": 6011,
    "name": "LEMBANG",
    "zip_code": "40391"
  },
  {
    "id": 6012,
    "name": "MEKARWANGI",
    "zip_code": "40391"
  },
  {
    "id": 6013,
    "name": "PAGERWANGI",
    "zip_code": "40391"
  },
  {
    "id": 6014,
    "name": "SUKAJAYA",
    "zip_code": "40391"
  },
  {
    "id": 6015,
    "name": "SUNTENJAYA",
    "zip_code": "40391"
  },
  {
    "id": 6016,
    "name": "WANGUNHARJA",
    "zip_code": "40391"
  },
  {
    "id": 6017,
    "name": "WANGUNSARI",
    "zip_code": "40391"
  }
]