[
  {
    "id": 56063,
    "name": "BUBUNG",
    "zip_code": "94717"
  },
  {
    "id": 56064,
    "name": "BUKIT MEMBUAL",
    "zip_code": "94717"
  },
  {
    "id": 56065,
    "name": "HANGA HANGA",
    "zip_code": "94717"
  },
  {
    "id": 56066,
    "name": "HANGA-HANGA PERMAI",
    "zip_code": "94717"
  },
  {
    "id": 56067,
    "name": "JOLE",
    "zip_code": "94717"
  },
  {
    "id": 56068,
    "name": "KOMPO",
    "zip_code": "94717"
  },
  {
    "id": 56069,
    "name": "MAAHAS",
    "zip_code": "94717"
  },
  {
    "id": 56070,
    "name": "SIMPONG",
    "zip_code": "94717"
  },
  {
    "id": 56071,
    "name": "TANJUNG TUWIS",
    "zip_code": "94717"
  },
  {
    "id": 56072,
    "name": "TOMBANG PERMAI",
    "zip_code": "94717"
  }
]