[
  {
    "id": 30272,
    "name": "DULAMAYO UTARA",
    "zip_code": "96181"
  },
  {
    "id": 30273,
    "name": "DUMATI",
    "zip_code": "96181"
  },
  {
    "id": 30274,
    "name": "LUPOYO",
    "zip_code": "96181"
  },
  {
    "id": 30275,
    "name": "MODELIDU (MODELLIDU)",
    "zip_code": "96181"
  },
  {
    "id": 30276,
    "name": "PANTUNGO",
    "zip_code": "96181"
  },
  {
    "id": 30277,
    "name": "PENTADIO BARAT",
    "zip_code": "96181"
  },
  {
    "id": 30278,
    "name": "PENTADIO TIMUR",
    "zip_code": "96181"
  },
  {
    "id": 30279,
    "name": "TALUMELITO",
    "zip_code": "96181"
  },
  {
    "id": 30280,
    "name": "TAPALULUO",
    "zip_code": "96181"
  },
  {
    "id": 30281,
    "name": "TIMUATO",
    "zip_code": "96181"
  },
  {
    "id": 30282,
    "name": "TINELO",
    "zip_code": "96181"
  },
  {
    "id": 30283,
    "name": "TONALA",
    "zip_code": "96181"
  },
  {
    "id": 30284,
    "name": "TULADENGGI",
    "zip_code": "96137"
  },
  {
    "id": 30285,
    "name": "ULAPATO A",
    "zip_code": "96181"
  },
  {
    "id": 30286,
    "name": "ULAPATO B",
    "zip_code": "96181"
  }
]