[
  {
    "id": 74495,
    "name": "CAHAYA MAKMUR",
    "zip_code": "34554"
  },
  {
    "id": 74496,
    "name": "CEMPAKA",
    "zip_code": "34554"
  },
  {
    "id": 74497,
    "name": "CEMPAKA BARAT",
    "zip_code": "34554"
  },
  {
    "id": 74498,
    "name": "CEMPAKA TIMUR",
    "zip_code": "34554"
  },
  {
    "id": 74499,
    "name": "LEPANG/LEMPANG TENGAH",
    "zip_code": "34554"
  },
  {
    "id": 74500,
    "name": "NEGARA AGUNG",
    "zip_code": "34554"
  },
  {
    "id": 74501,
    "name": "SRI AGUNG",
    "zip_code": "34554"
  },
  {
    "id": 74502,
    "name": "SRI JAYA",
    "zip_code": "34554"
  },
  {
    "id": 74503,
    "name": "SUKAJAYA",
    "zip_code": "34554"
  }
]