[
  {
    "id": 8167,
    "name": "BANTARJATI",
    "zip_code": "16153"
  },
  {
    "id": 8168,
    "name": "CIBULUH",
    "zip_code": "16151"
  },
  {
    "id": 8169,
    "name": "CILUAR",
    "zip_code": "16156"
  },
  {
    "id": 8170,
    "name": "CIMAHPAR",
    "zip_code": "16155"
  },
  {
    "id": 8171,
    "name": "CIPARIGI",
    "zip_code": "16157"
  },
  {
    "id": 8172,
    "name": "KEDUNGHALANG",
    "zip_code": "16158"
  },
  {
    "id": 8173,
    "name": "TANAH BARU",
    "zip_code": "16154"
  },
  {
    "id": 8174,
    "name": "TEGAL GUNDIL",
    "zip_code": "16152"
  }
]