[
  {
    "id": 27912,
    "name": "BANUA SIBOHOU",
    "zip_code": "22816"
  },
  {
    "id": 27913,
    "name": "BERUA",
    "zip_code": "22816"
  },
  {
    "id": 27914,
    "name": "DAHANA HILIGODU",
    "zip_code": "22816"
  },
  {
    "id": 27915,
    "name": "ESIWA",
    "zip_code": "22816"
  },
  {
    "id": 27916,
    "name": "HILIBANUA",
    "zip_code": "22816"
  },
  {
    "id": 27917,
    "name": "LASARA",
    "zip_code": "22816"
  },
  {
    "id": 27918,
    "name": "NAMOHALU",
    "zip_code": "22816"
  },
  {
    "id": 27919,
    "name": "ORAHILI",
    "zip_code": "22816"
  },
  {
    "id": 27920,
    "name": "SISARAHILI",
    "zip_code": "22816"
  },
  {
    "id": 27921,
    "name": "SISOBAHILI",
    "zip_code": "22817"
  },
  {
    "id": 27922,
    "name": "TUHENAKHE I",
    "zip_code": "22816"
  }
]