[
  {
    "id": 77324,
    "name": "CIBEBER",
    "zip_code": "46195"
  },
  {
    "id": 77325,
    "name": "CIDADALI",
    "zip_code": "46195"
  },
  {
    "id": 77326,
    "name": "CIKADU",
    "zip_code": "46195"
  },
  {
    "id": 77327,
    "name": "CIKALONG",
    "zip_code": "46195"
  },
  {
    "id": 77328,
    "name": "CIKANCRA",
    "zip_code": "46195"
  },
  {
    "id": 77329,
    "name": "CIMANUK",
    "zip_code": "46195"
  },
  {
    "id": 77330,
    "name": "KALAPAGENEP",
    "zip_code": "46195"
  },
  {
    "id": 77331,
    "name": "KUBANGSARI",
    "zip_code": "46195"
  },
  {
    "id": 77332,
    "name": "MANDALAJAYA",
    "zip_code": "46195"
  },
  {
    "id": 77333,
    "name": "PANYIARAN",
    "zip_code": "46195"
  },
  {
    "id": 77334,
    "name": "SINDANGJAYA",
    "zip_code": "46195"
  },
  {
    "id": 77335,
    "name": "SINGKIR",
    "zip_code": "46195"
  },
  {
    "id": 77336,
    "name": "TONJONGSARI",
    "zip_code": "46195"
  }
]