[
  {
    "id": 68625,
    "name": "BOJANEGARA",
    "zip_code": "53372"
  },
  {
    "id": 68626,
    "name": "DAWUHAN",
    "zip_code": "53372"
  },
  {
    "id": 68627,
    "name": "GEMURUH",
    "zip_code": "53372"
  },
  {
    "id": 68628,
    "name": "KALITINGGAR",
    "zip_code": "53372"
  },
  {
    "id": 68629,
    "name": "KALITINGGAR KIDUL",
    "zip_code": "53372"
  },
  {
    "id": 68630,
    "name": "KARANGGAMBAS",
    "zip_code": "53372"
  },
  {
    "id": 68631,
    "name": "KARANGJAMBE",
    "zip_code": "53372"
  },
  {
    "id": 68632,
    "name": "KARANGPULE",
    "zip_code": "53372"
  },
  {
    "id": 68633,
    "name": "KARANGSENTUL",
    "zip_code": "53372"
  },
  {
    "id": 68634,
    "name": "MIPIRAN",
    "zip_code": "53372"
  },
  {
    "id": 68635,
    "name": "PADAMARA",
    "zip_code": "53372"
  },
  {
    "id": 68636,
    "name": "PRIGI",
    "zip_code": "53372"
  },
  {
    "id": 68637,
    "name": "PURBAYASA",
    "zip_code": "53372"
  },
  {
    "id": 68638,
    "name": "SOKAWERA",
    "zip_code": "53372"
  }
]