[
  {
    "id": 31151,
    "name": "BANJAR",
    "zip_code": "68454"
  },
  {
    "id": 31152,
    "name": "GUMUK",
    "zip_code": "68454"
  },
  {
    "id": 31153,
    "name": "JELUN",
    "zip_code": "68454"
  },
  {
    "id": 31154,
    "name": "KLUNCING",
    "zip_code": "68454"
  },
  {
    "id": 31155,
    "name": "LICIN",
    "zip_code": "68454"
  },
  {
    "id": 31156,
    "name": "PAKEL",
    "zip_code": "68454"
  },
  {
    "id": 31157,
    "name": "SEGOBANG",
    "zip_code": "68454"
  },
  {
    "id": 31158,
    "name": "TAMANSARI",
    "zip_code": "68454"
  }
]