[
  {
    "id": 18614,
    "name": "BADUR",
    "zip_code": "42363"
  },
  {
    "id": 18615,
    "name": "CEMPAKA",
    "zip_code": "42363"
  },
  {
    "id": 18616,
    "name": "CIBARANI",
    "zip_code": "42363"
  },
  {
    "id": 18617,
    "name": "CIRINTEN",
    "zip_code": "42363"
  },
  {
    "id": 18618,
    "name": "DATARCAE",
    "zip_code": "42363"
  },
  {
    "id": 18619,
    "name": "KADUDAMAS",
    "zip_code": "42363"
  },
  {
    "id": 18620,
    "name": "KARANGNUNGGAL",
    "zip_code": "42363"
  },
  {
    "id": 18621,
    "name": "KAROYA",
    "zip_code": "42363"
  },
  {
    "id": 18622,
    "name": "NANGERANG",
    "zip_code": "42363"
  },
  {
    "id": 18623,
    "name": "PARAKANLIMA",
    "zip_code": "42363"
  }
]