[
  {
    "id": 16447,
    "name": "CIMARANTEN",
    "zip_code": "45592"
  },
  {
    "id": 16448,
    "name": "CIPICUNG",
    "zip_code": "45592"
  },
  {
    "id": 16449,
    "name": "KAROYA",
    "zip_code": "45592"
  },
  {
    "id": 16450,
    "name": "MEKARSARI",
    "zip_code": "45576"
  },
  {
    "id": 16451,
    "name": "MUNCANGELA",
    "zip_code": "45592"
  },
  {
    "id": 16452,
    "name": "PAMULIHAN",
    "zip_code": "45592"
  },
  {
    "id": 16453,
    "name": "SALAREUMA",
    "zip_code": "45592"
  },
  {
    "id": 16454,
    "name": "SUGANANGAN",
    "zip_code": "45592"
  },
  {
    "id": 16455,
    "name": "SUKAMUKTI",
    "zip_code": "45592"
  },
  {
    "id": 16456,
    "name": "SUSUKAN",
    "zip_code": "45592"
  }
]