[
  {
    "id": 57801,
    "name": "BALAMOA",
    "zip_code": "94361"
  },
  {
    "id": 57802,
    "name": "BALAROA PEWENU",
    "zip_code": "94361"
  },
  {
    "id": 57803,
    "name": "BALUMPEWA",
    "zip_code": "94361"
  },
  {
    "id": 57804,
    "name": "BOBO",
    "zip_code": "94361"
  },
  {
    "id": 57805,
    "name": "KALEKE",
    "zip_code": "94361"
  },
  {
    "id": 57806,
    "name": "KALUKU TINGGU",
    "zip_code": "94361"
  },
  {
    "id": 57807,
    "name": "LUKU",
    "zip_code": "94361"
  },
  {
    "id": 57808,
    "name": "MANTIKOLE",
    "zip_code": "94361"
  },
  {
    "id": 57809,
    "name": "PESAKU",
    "zip_code": "94361"
  },
  {
    "id": 57810,
    "name": "PEWUNU",
    "zip_code": "94361"
  },
  {
    "id": 57811,
    "name": "RARAMPADENDE",
    "zip_code": "94361"
  },
  {
    "id": 57812,
    "name": "SIBONU",
    "zip_code": "94361"
  }
]