[
  {
    "id": 24957,
    "name": "HONGGOLUK",
    "zip_code": "99582"
  },
  {
    "id": 24958,
    "name": "HONTULUN",
    "zip_code": "99582"
  },
  {
    "id": 24959,
    "name": "SOLINGGUL (SOLINGUL)",
    "zip_code": "99582"
  },
  {
    "id": 24960,
    "name": "WALMA",
    "zip_code": "99582"
  },
  {
    "id": 24961,
    "name": "WERENE",
    "zip_code": "99582"
  },
  {
    "id": 24962,
    "name": "WERI",
    "zip_code": "99582"
  },
  {
    "id": 24963,
    "name": "WEWASI",
    "zip_code": "99582"
  },
  {
    "id": 24964,
    "name": "YETEHUP",
    "zip_code": "99582"
  }
]