[
  {
    "id": 70784,
    "name": "BAPELLE",
    "zip_code": "69254"
  },
  {
    "id": 70785,
    "name": "GUNUNG RANCAK",
    "zip_code": "69254"
  },
  {
    "id": 70786,
    "name": "JELGUNG",
    "zip_code": "69254"
  },
  {
    "id": 70787,
    "name": "LEPELLE",
    "zip_code": "69254"
  },
  {
    "id": 70788,
    "name": "PANDIYANGAN",
    "zip_code": "69254"
  },
  {
    "id": 70789,
    "name": "ROBATAL",
    "zip_code": "69254"
  },
  {
    "id": 70790,
    "name": "SAWAH TENGAH",
    "zip_code": "69254"
  },
  {
    "id": 70791,
    "name": "TORJUNAN",
    "zip_code": "69254"
  },
  {
    "id": 70792,
    "name": "TRAGIH",
    "zip_code": "69254"
  }
]