[
  {
    "id": 78457,
    "name": "BILIFITU",
    "zip_code": "97854"
  },
  {
    "id": 78458,
    "name": "DAMULI",
    "zip_code": "97854"
  },
  {
    "id": 78459,
    "name": "GEMIA",
    "zip_code": "97854"
  },
  {
    "id": 78460,
    "name": "MALIFORO",
    "zip_code": "97854"
  },
  {
    "id": 78461,
    "name": "MASURE",
    "zip_code": "97854"
  },
  {
    "id": 78462,
    "name": "NURSIFA",
    "zip_code": "97854"
  },
  {
    "id": 78463,
    "name": "PALO",
    "zip_code": "97854"
  },
  {
    "id": 78464,
    "name": "PANTURA JAYA",
    "zip_code": "97854"
  },
  {
    "id": 78465,
    "name": "PENITI",
    "zip_code": "97854"
  },
  {
    "id": 78466,
    "name": "SAKAM",
    "zip_code": "97854"
  },
  {
    "id": 78467,
    "name": "TEPELEO BATUDUA",
    "zip_code": "97854"
  },
  {
    "id": 78468,
    "name": "TILOPE (TEPELEO)",
    "zip_code": "97854"
  }
]