[
  {
    "id": 61702,
    "name": "ANDONG",
    "zip_code": "57384"
  },
  {
    "id": 61703,
    "name": "BEJI",
    "zip_code": "57384"
  },
  {
    "id": 61704,
    "name": "GONDANG RAWE",
    "zip_code": "57384"
  },
  {
    "id": 61705,
    "name": "KACANGAN",
    "zip_code": "57384"
  },
  {
    "id": 61706,
    "name": "KADIPATEN",
    "zip_code": "57384"
  },
  {
    "id": 61707,
    "name": "KEDUNGDOWO",
    "zip_code": "57384"
  },
  {
    "id": 61708,
    "name": "KUNTI",
    "zip_code": "57384"
  },
  {
    "id": 61709,
    "name": "MOJO",
    "zip_code": "57384"
  },
  {
    "id": 61710,
    "name": "MUNGGUR",
    "zip_code": "57384"
  },
  {
    "id": 61711,
    "name": "PAKANG",
    "zip_code": "57384"
  },
  {
    "id": 61712,
    "name": "PAKEL",
    "zip_code": "57384"
  },
  {
    "id": 61713,
    "name": "PELEMREJO",
    "zip_code": "57384"
  },
  {
    "id": 61714,
    "name": "PRANGGONG",
    "zip_code": "57384"
  },
  {
    "id": 61715,
    "name": "SEMAWUNG",
    "zip_code": "57384"
  },
  {
    "id": 61716,
    "name": "SEMPU",
    "zip_code": "57384"
  },
  {
    "id": 61717,
    "name": "SENGGRONG",
    "zip_code": "57384"
  }
]