[
  {
    "id": 80756,
    "name": "ALLESALEWOE",
    "zip_code": "91672"
  },
  {
    "id": 80757,
    "name": "BAPANGI",
    "zip_code": "91672"
  },
  {
    "id": 80758,
    "name": "BILOKKA",
    "zip_code": "91672"
  },
  {
    "id": 80759,
    "name": "CENRANA",
    "zip_code": "91672"
  },
  {
    "id": 80760,
    "name": "CORAWALI",
    "zip_code": "91672"
  },
  {
    "id": 80761,
    "name": "LAJONGA",
    "zip_code": "91672"
  },
  {
    "id": 80762,
    "name": "LISE",
    "zip_code": "91672"
  },
  {
    "id": 80763,
    "name": "WANIO",
    "zip_code": "91672"
  },
  {
    "id": 80764,
    "name": "WANIO TIMORENG",
    "zip_code": "91672"
  },
  {
    "id": 80765,
    "name": "WETTEE",
    "zip_code": "91672"
  }
]