[
  {
    "id": 24552,
    "name": "AMUMA",
    "zip_code": "99571"
  },
  {
    "id": 24553,
    "name": "BALUM ERANG",
    "zip_code": "99571"
  },
  {
    "id": 24554,
    "name": "GOLOWEN",
    "zip_code": "99571"
  },
  {
    "id": 24555,
    "name": "HARAPAN",
    "zip_code": "99571"
  },
  {
    "id": 24556,
    "name": "KINIKA",
    "zip_code": "99571"
  },
  {
    "id": 24557,
    "name": "ORUGAI",
    "zip_code": "99571"
  },
  {
    "id": 24558,
    "name": "PLAU",
    "zip_code": "99571"
  },
  {
    "id": 24559,
    "name": "SAGASAL",
    "zip_code": "99571"
  },
  {
    "id": 24560,
    "name": "SARMUGE",
    "zip_code": "99571"
  },
  {
    "id": 24561,
    "name": "SILORIN",
    "zip_code": "99571"
  },
  {
    "id": 24562,
    "name": "TOLIKAPURA (TALIKAPURA)",
    "zip_code": "99571"
  },
  {
    "id": 24563,
    "name": "WAEKLEK",
    "zip_code": "99571"
  },
  {
    "id": 24564,
    "name": "WISIKMA",
    "zip_code": "99571"
  }
]