[
  {
    "id": 73734,
    "name": "DINGO NARAMA",
    "zip_code": "99910"
  },
  {
    "id": 73735,
    "name": "HANGAITJI",
    "zip_code": "99910"
  },
  {
    "id": 73736,
    "name": "KEBUN SIRIH",
    "zip_code": "99910"
  },
  {
    "id": 73737,
    "name": "KOPERAPOKA",
    "zip_code": "99910"
  },
  {
    "id": 73738,
    "name": "KWAMKI",
    "zip_code": "99910"
  },
  {
    "id": 73739,
    "name": "MINABUA",
    "zip_code": "99910"
  },
  {
    "id": 73740,
    "name": "NAYARO",
    "zip_code": "99910"
  },
  {
    "id": 73741,
    "name": "OTOMONA",
    "zip_code": "99910"
  },
  {
    "id": 73742,
    "name": "PASAR SENTRAL",
    "zip_code": "99910"
  },
  {
    "id": 73743,
    "name": "PERINTIS",
    "zip_code": "99910"
  },
  {
    "id": 73744,
    "name": "SEMPAN",
    "zip_code": "99910"
  },
  {
    "id": 73745,
    "name": "TIMIKA INDAH",
    "zip_code": "99910"
  },
  {
    "id": 73746,
    "name": "TIMIKA JAYA",
    "zip_code": "99910"
  },
  {
    "id": 73747,
    "name": "WANAGON",
    "zip_code": "99910"
  }
]