[
  {
    "id": 28601,
    "name": "ARITONANG",
    "zip_code": "22476"
  },
  {
    "id": 28602,
    "name": "BARIBA NIAEK",
    "zip_code": "22476"
  },
  {
    "id": 28603,
    "name": "BATU BINUMBUN",
    "zip_code": "22476"
  },
  {
    "id": 28604,
    "name": "DOLOK MARTUMBUR",
    "zip_code": "22476"
  },
  {
    "id": 28605,
    "name": "HUTA GINJANG",
    "zip_code": "22476"
  },
  {
    "id": 28606,
    "name": "HUTA LONTUNG",
    "zip_code": "22476"
  },
  {
    "id": 28607,
    "name": "HUTA NAGODANG",
    "zip_code": "22476"
  },
  {
    "id": 28608,
    "name": "PAPANDE",
    "zip_code": "22476"
  },
  {
    "id": 28609,
    "name": "SAMPURAN",
    "zip_code": "22476"
  },
  {
    "id": 28610,
    "name": "SIBANDANG",
    "zip_code": "22476"
  },
  {
    "id": 28611,
    "name": "SILALI TORUAN",
    "zip_code": "22476"
  },
  {
    "id": 28612,
    "name": "SILANDO",
    "zip_code": "22476"
  },
  {
    "id": 28613,
    "name": "SIMATUPANG",
    "zip_code": "22476"
  },
  {
    "id": 28614,
    "name": "SITANGGOR",
    "zip_code": "22476"
  },
  {
    "id": 28615,
    "name": "UNTE MUNGKUR",
    "zip_code": "22476"
  }
]