[
  {
    "id": 4742,
    "name": "LUWUK"
  },
  {
    "id": 4743,
    "name": "BALANTAK"
  },
  {
    "id": 4744,
    "name": "BATUI"
  },
  {
    "id": 4745,
    "name": "BUNTA"
  },
  {
    "id": 4746,
    "name": "KINTOM"
  },
  {
    "id": 4747,
    "name": "LAMALA"
  },
  {
    "id": 4748,
    "name": "PAGIMANA"
  },
  {
    "id": 4749,
    "name": "BUALEMO (BOALEMO)"
  },
  {
    "id": 4750,
    "name": "TOILI"
  },
  {
    "id": 4751,
    "name": "BALANTAK SELATAN"
  },
  {
    "id": 4752,
    "name": "BALANTAK UTARA"
  },
  {
    "id": 4753,
    "name": "BATUI SELATAN"
  },
  {
    "id": 4754,
    "name": "LOBU"
  },
  {
    "id": 4755,
    "name": "LUWUK SELATAN"
  },
  {
    "id": 4756,
    "name": "LUWUK TIMUR"
  },
  {
    "id": 4757,
    "name": "LUWUK UTARA"
  },
  {
    "id": 4758,
    "name": "MANTOH"
  },
  {
    "id": 4759,
    "name": "MASAMA"
  },
  {
    "id": 4760,
    "name": "MOILONG"
  },
  {
    "id": 4761,
    "name": "NAMBO"
  },
  {
    "id": 4762,
    "name": "NUHON"
  },
  {
    "id": 4763,
    "name": "SIMPANG RAYA"
  },
  {
    "id": 4764,
    "name": "TOILI BARAT"
  }
]