[
  {
    "id": 69037,
    "name": "AMBOKEMBANG",
    "zip_code": "51173"
  },
  {
    "id": 69038,
    "name": "BUGANGAN/BUNGANGAN",
    "zip_code": "51173"
  },
  {
    "id": 69039,
    "name": "KARANGDOWO",
    "zip_code": "51173"
  },
  {
    "id": 69040,
    "name": "KEDUNG PATANGEWU",
    "zip_code": "51173"
  },
  {
    "id": 69041,
    "name": "KEDUNGWUNI BARAT",
    "zip_code": "51173"
  },
  {
    "id": 69042,
    "name": "KEDUNGWUNI TIMUR",
    "zip_code": "51173"
  },
  {
    "id": 69043,
    "name": "KWAYANGAN",
    "zip_code": "51173"
  },
  {
    "id": 69044,
    "name": "LANGKAP",
    "zip_code": "51173"
  },
  {
    "id": 69045,
    "name": "PAJOMBLANGAN",
    "zip_code": "51173"
  },
  {
    "id": 69046,
    "name": "PAKISPUTIH",
    "zip_code": "51173"
  },
  {
    "id": 69047,
    "name": "PEKAJANGAN",
    "zip_code": "51173"
  },
  {
    "id": 69048,
    "name": "PODO",
    "zip_code": "51173"
  },
  {
    "id": 69049,
    "name": "PROTO",
    "zip_code": "51173"
  },
  {
    "id": 69050,
    "name": "RENGAS",
    "zip_code": "51173"
  },
  {
    "id": 69051,
    "name": "ROWOCACING",
    "zip_code": "51173"
  },
  {
    "id": 69052,
    "name": "SALAKBROJO",
    "zip_code": "51173"
  },
  {
    "id": 69053,
    "name": "TANGKIL KULON",
    "zip_code": "51173"
  },
  {
    "id": 69054,
    "name": "TANGKIL TENGAH",
    "zip_code": "51173"
  },
  {
    "id": 69055,
    "name": "TOSARAN",
    "zip_code": "51173"
  }
]