[
  {
    "id": 15490,
    "name": "ARONGAN",
    "zip_code": "23661"
  },
  {
    "id": 15491,
    "name": "COT RAMBONG (COT ME)",
    "zip_code": "23661"
  },
  {
    "id": 15492,
    "name": "GAMPONG LHOK",
    "zip_code": "23661"
  },
  {
    "id": 15493,
    "name": "GUBANG GAJAH",
    "zip_code": "23661"
  },
  {
    "id": 15494,
    "name": "JATIREJO",
    "zip_code": "23661"
  },
  {
    "id": 15495,
    "name": "KUALA BARO",
    "zip_code": "23661"
  },
  {
    "id": 15496,
    "name": "KUALA TRANG",
    "zip_code": "23661"
  },
  {
    "id": 15497,
    "name": "KUALA TUHA",
    "zip_code": "23661"
  },
  {
    "id": 15498,
    "name": "LANGKAK",
    "zip_code": "23661"
  },
  {
    "id": 15499,
    "name": "LUENG T BEN",
    "zip_code": "23661"
  },
  {
    "id": 15500,
    "name": "PADANG PANYANG",
    "zip_code": "23661"
  },
  {
    "id": 15501,
    "name": "PADANG RUBEEK",
    "zip_code": "23661"
  },
  {
    "id": 15502,
    "name": "PULO",
    "zip_code": "23661"
  },
  {
    "id": 15503,
    "name": "PURWODADI",
    "zip_code": "23661"
  },
  {
    "id": 15504,
    "name": "PURWOSARI",
    "zip_code": "23661"
  },
  {
    "id": 15505,
    "name": "SUAK PUNTONG",
    "zip_code": "23661"
  }
]