[
  {
    "id": 29011,
    "name": "AEK SIMOTUNG",
    "zip_code": "22758"
  },
  {
    "id": 29012,
    "name": "BATANG PARSULUMAN",
    "zip_code": "22758"
  },
  {
    "id": 29013,
    "name": "DAMPARAN HAUNATAS",
    "zip_code": "22758"
  },
  {
    "id": 29014,
    "name": "HUTA HOMBANG",
    "zip_code": "22758"
  },
  {
    "id": 29015,
    "name": "HUTA POHAN",
    "zip_code": "22758"
  },
  {
    "id": 29016,
    "name": "PADANG MANDAILING GARUGUR",
    "zip_code": "22758"
  },
  {
    "id": 29017,
    "name": "PARAU SORAT SITABO TABO",
    "zip_code": "22758"
  },
  {
    "id": 29018,
    "name": "PASAR SIMANGAMBAT",
    "zip_code": "22758"
  },
  {
    "id": 29019,
    "name": "PINTU PADANG MANDALASENA",
    "zip_code": "22758"
  },
  {
    "id": 29020,
    "name": "PURBASINOMBA SENA",
    "zip_code": "22758"
  },
  {
    "id": 29021,
    "name": "SAUT BANUA SIMANOSOR",
    "zip_code": "22758"
  },
  {
    "id": 29022,
    "name": "SIDAPDAP SIMANOSOR",
    "zip_code": "22758"
  },
  {
    "id": 29023,
    "name": "SILANGKITANG TAMBISKI",
    "zip_code": "22758"
  },
  {
    "id": 29024,
    "name": "SIMANGAMBAT GODANG",
    "zip_code": "22758"
  },
  {
    "id": 29025,
    "name": "SOMBA DEBATA PURBA",
    "zip_code": "22758"
  },
  {
    "id": 29026,
    "name": "SUNGE SIGIRING GIRING",
    "zip_code": "22758"
  },
  {
    "id": 29027,
    "name": "ULU MAMIS SITUNGGALING",
    "zip_code": "22758"
  },
  {
    "id": 82817,
    "name": "PASAR SIPAGIMBAR",
    "zip_code": "22758"
  }
]