[
  {
    "id": 39678,
    "name": "PANGU",
    "zip_code": "95995"
  },
  {
    "id": 39679,
    "name": "PANGU DUA",
    "zip_code": "95995"
  },
  {
    "id": 39680,
    "name": "PANGU SATU",
    "zip_code": "95995"
  },
  {
    "id": 39681,
    "name": "WIOI DUA",
    "zip_code": "95995"
  },
  {
    "id": 39682,
    "name": "WIOI SATU",
    "zip_code": "95995"
  },
  {
    "id": 39683,
    "name": "WIOI TIGA",
    "zip_code": "95995"
  },
  {
    "id": 39684,
    "name": "WIOI TIMUR",
    "zip_code": "95995"
  },
  {
    "id": 39685,
    "name": "WIOY (WIOI)",
    "zip_code": "95995"
  },
  {
    "id": 39686,
    "name": "WONGKAI SATU",
    "zip_code": "95995"
  },
  {
    "id": 39687,
    "name": "WONGKAY (WONGKAI)",
    "zip_code": "95995"
  }
]