[
  {
    "id": 42479,
    "name": "AEK KORSIK",
    "zip_code": "21455"
  },
  {
    "id": 42480,
    "name": "BANDAR SELAMAT",
    "zip_code": "21455"
  },
  {
    "id": 42481,
    "name": "KARANG AYER (ANYAR)",
    "zip_code": "21455"
  },
  {
    "id": 42482,
    "name": "PADANG MANINJAU",
    "zip_code": "21455"
  },
  {
    "id": 42483,
    "name": "PERKEBUNAN PADANG HALABAN",
    "zip_code": "21455"
  },
  {
    "id": 42484,
    "name": "PERKEBUNAN PANIGORAN",
    "zip_code": "21455"
  },
  {
    "id": 42485,
    "name": "PURWO REJO",
    "zip_code": "21455"
  },
  {
    "id": 42486,
    "name": "SIDOMULYO",
    "zip_code": "21455"
  }
]