[
  {
    "id": 60113,
    "name": "GENENG WARU",
    "zip_code": "67152"
  },
  {
    "id": 60114,
    "name": "KALISAT",
    "zip_code": "67152"
  },
  {
    "id": 60115,
    "name": "KANIGORO",
    "zip_code": "67152"
  },
  {
    "id": 60116,
    "name": "KEDUNG BANTENG",
    "zip_code": "67152"
  },
  {
    "id": 60117,
    "name": "KRENGIH",
    "zip_code": "67152"
  },
  {
    "id": 60118,
    "name": "MOJOPARON",
    "zip_code": "67152"
  },
  {
    "id": 60119,
    "name": "OROBULU",
    "zip_code": "67152"
  },
  {
    "id": 60120,
    "name": "OROOMBO KULON",
    "zip_code": "67152"
  },
  {
    "id": 60121,
    "name": "OROOMBO WETAN",
    "zip_code": "67152"
  },
  {
    "id": 60122,
    "name": "PAJARAN",
    "zip_code": "67152"
  },
  {
    "id": 60123,
    "name": "PANDEAN",
    "zip_code": "67152"
  },
  {
    "id": 60124,
    "name": "PEJANGKUNGAN",
    "zip_code": "67152"
  },
  {
    "id": 60125,
    "name": "PEKOREN",
    "zip_code": "67152"
  },
  {
    "id": 60126,
    "name": "REMBANG",
    "zip_code": "67152"
  },
  {
    "id": 60127,
    "name": "SIYAR",
    "zip_code": "67152"
  },
  {
    "id": 60128,
    "name": "SUMBER GLAGAH",
    "zip_code": "67152"
  },
  {
    "id": 60129,
    "name": "TAMPUNG",
    "zip_code": "67152"
  }
]