[
  {
    "id": 26093,
    "name": "BAN",
    "zip_code": "80853"
  },
  {
    "id": 26094,
    "name": "BATU RINGGIT",
    "zip_code": "80853"
  },
  {
    "id": 26095,
    "name": "DUKUH",
    "zip_code": "80853"
  },
  {
    "id": 26096,
    "name": "KUBU",
    "zip_code": "80853"
  },
  {
    "id": 26097,
    "name": "SUKADANA",
    "zip_code": "80853"
  },
  {
    "id": 26098,
    "name": "TIANYAR BARAT",
    "zip_code": "80853"
  },
  {
    "id": 26099,
    "name": "TIANYAR TENGAH",
    "zip_code": "80853"
  },
  {
    "id": 26100,
    "name": "TIANYAR TIMUR",
    "zip_code": "80853"
  },
  {
    "id": 26101,
    "name": "TULAMBEN",
    "zip_code": "80853"
  }
]