[
  {
    "id": 69621,
    "name": "BALIKTERUS",
    "zip_code": "61181"
  },
  {
    "id": 69622,
    "name": "BULULANJANG",
    "zip_code": "61181"
  },
  {
    "id": 69623,
    "name": "DAUN",
    "zip_code": "61181"
  },
  {
    "id": 69624,
    "name": "DEKATAGUNG",
    "zip_code": "61181"
  },
  {
    "id": 69625,
    "name": "GUNUNGTEGUH",
    "zip_code": "61181"
  },
  {
    "id": 69626,
    "name": "KEBON TELUK DALAM",
    "zip_code": "61181"
  },
  {
    "id": 69627,
    "name": "KOTA KUSUMA",
    "zip_code": "61181"
  },
  {
    "id": 69628,
    "name": "KUMALASA",
    "zip_code": "61181"
  },
  {
    "id": 69629,
    "name": "LEBAK",
    "zip_code": "61181"
  },
  {
    "id": 69630,
    "name": "PATARSELAMAT",
    "zip_code": "61181"
  },
  {
    "id": 69631,
    "name": "PUDAKIT BARAT",
    "zip_code": "61181"
  },
  {
    "id": 69632,
    "name": "PUDAKIT TIMUR",
    "zip_code": "61181"
  },
  {
    "id": 69633,
    "name": "SAWAHMULYA",
    "zip_code": "61181"
  },
  {
    "id": 69634,
    "name": "SIDOGEDUNG BATU",
    "zip_code": "61181"
  },
  {
    "id": 69635,
    "name": "SUNGAI RUJING",
    "zip_code": "61181"
  },
  {
    "id": 69636,
    "name": "SUNGAI TELUK",
    "zip_code": "61181"
  },
  {
    "id": 69637,
    "name": "SUWARI",
    "zip_code": "61181"
  }
]