[
  {
    "id": 77189,
    "name": "CIKADONGDONG",
    "zip_code": "46418"
  },
  {
    "id": 77190,
    "name": "CIKUNIR",
    "zip_code": "46418"
  },
  {
    "id": 77191,
    "name": "CIKUNTEN",
    "zip_code": "46414"
  },
  {
    "id": 77192,
    "name": "CINTARAJA",
    "zip_code": "46417"
  },
  {
    "id": 77193,
    "name": "CIPAKAT",
    "zip_code": "46417"
  },
  {
    "id": 77194,
    "name": "SINGAPARNA",
    "zip_code": "46411"
  },
  {
    "id": 77195,
    "name": "SINGASARI",
    "zip_code": "46412"
  },
  {
    "id": 77196,
    "name": "SUKAASIH",
    "zip_code": "46415"
  },
  {
    "id": 77197,
    "name": "SUKAHERANG",
    "zip_code": "46413"
  },
  {
    "id": 77198,
    "name": "SUKAMULYA",
    "zip_code": "46416"
  }
]