[
  {
    "id": 29281,
    "name": "BATAHAN",
    "zip_code": "22994"
  },
  {
    "id": 29282,
    "name": "BOTUNG",
    "zip_code": "22994"
  },
  {
    "id": 29283,
    "name": "GADING BAIN",
    "zip_code": "22994"
  },
  {
    "id": 29284,
    "name": "GUNUNG TUA MS",
    "zip_code": "22994"
  },
  {
    "id": 29285,
    "name": "GUNUNG TUA SM",
    "zip_code": "22994"
  },
  {
    "id": 29286,
    "name": "HUSOR TOLANG (UNSOR TOLAN)",
    "zip_code": "22994"
  },
  {
    "id": 29287,
    "name": "HUTA BARINGIN TB",
    "zip_code": "22994"
  },
  {
    "id": 29288,
    "name": "HUTA DANGKA",
    "zip_code": "22994"
  },
  {
    "id": 29289,
    "name": "HUTA PADANG SM",
    "zip_code": "22994"
  },
  {
    "id": 29290,
    "name": "HUTA PULI",
    "zip_code": "22994"
  },
  {
    "id": 29291,
    "name": "HUTA PUNGKUT JAE",
    "zip_code": "22994"
  },
  {
    "id": 29292,
    "name": "HUTA PUNGKUT JULU",
    "zip_code": "22994"
  },
  {
    "id": 29293,
    "name": "HUTA PUNGKUT TONGA",
    "zip_code": "22994"
  },
  {
    "id": 29294,
    "name": "HUTA RIMBARU SM",
    "zip_code": "22994"
  },
  {
    "id": 29295,
    "name": "MANAMBIN",
    "zip_code": "22994"
  },
  {
    "id": 29296,
    "name": "MUARA BOTUNG",
    "zip_code": "22994"
  },
  {
    "id": 29297,
    "name": "MUARA POTAN",
    "zip_code": "22994"
  },
  {
    "id": 29298,
    "name": "MUARA PUNGKUT",
    "zip_code": "22994"
  },
  {
    "id": 29299,
    "name": "MUARA SALADI",
    "zip_code": "22994"
  },
  {
    "id": 29300,
    "name": "MUARA SIAMBAK",
    "zip_code": "22994"
  },
  {
    "id": 29301,
    "name": "PADANG BULAN",
    "zip_code": "22994"
  },
  {
    "id": 29302,
    "name": "PAGAR GUNUNG",
    "zip_code": "22994"
  },
  {
    "id": 29303,
    "name": "PASAR KOTANOPAN",
    "zip_code": "22994"
  },
  {
    "id": 29304,
    "name": "PATIALO",
    "zip_code": "22994"
  },
  {
    "id": 29305,
    "name": "SABA DOLOK",
    "zip_code": "22994"
  },
  {
    "id": 29306,
    "name": "SAYUR MAINCAT",
    "zip_code": "22994"
  },
  {
    "id": 29307,
    "name": "SIBIO-BIO",
    "zip_code": "22994"
  },
  {
    "id": 29308,
    "name": "SIMANDOLAN",
    "zip_code": "22994"
  },
  {
    "id": 29309,
    "name": "SIMPANG TOLANG JAE",
    "zip_code": "22994"
  },
  {
    "id": 29310,
    "name": "SIMPANG TOLANG JULU",
    "zip_code": "22994"
  },
  {
    "id": 29311,
    "name": "SINGENGU JAE",
    "zip_code": "22994"
  },
  {
    "id": 29312,
    "name": "SINGENGU JULU",
    "zip_code": "22994"
  },
  {
    "id": 29313,
    "name": "TAMBANG BUSTAK",
    "zip_code": "22994"
  },
  {
    "id": 29314,
    "name": "TAMIANG",
    "zip_code": "22994"
  },
  {
    "id": 29315,
    "name": "TOBANG",
    "zip_code": "22994"
  },
  {
    "id": 29316,
    "name": "UJUNG MARISI",
    "zip_code": "22994"
  },
  {
    "id": 29317,
    "name": "USOR TOLANG",
    "zip_code": "22994"
  }
]